{"nombre_cliente": "Feliciano Saucedo Monge", "dni_cliente": "17691890Z", "calle_cliente": "Calle Zarza", "cp_cliente": "27153", "población_cliente": "Outeiro", "provincia_cliente": "Lugo", "nombre_comercializadora": null, "cif_comercializadora": "F37560554", "dirección_comercializadora": "PLAZA EGIDO S/N,", "cp_comercializadora": "37173", "población_comercializadora": "Salamanca", "provincia_comercializadora": "Salamanca", "número_factura": "U7580052916", "inicio_periodo": "03.06.2017", "fin_periodo": "03.07.2017", "importe_factura": "72,17", "fecha_cargo": "08.07.2017", "consumo_periodo": 175, "potencia_contratada": "5,266"}