{"nombre_cliente": "Apolonia Villareal Collado", "dni_cliente": "64875522C", "calle_cliente": null, "cp_cliente": null, "población_cliente": null, "provincia_cliente": null, "nombre_comercializadora": null, "cif_comercializadora": "A74255282", "dirección_comercializadora": "C\\ Poeta Joan Maragall, 1, 3º Sur (Edificio Eurocentro),", "cp_comercializadora": "28020", "población_comercializadora": "Madrid", "provincia_comercializadora": "Madrid", "número_factura": "Q2357373784", "inicio_periodo": "13.01.2007", "fin_periodo": "14.03.2007", "importe_factura": "170,00", "fecha_cargo": "19.03.2007", "consumo_periodo": 476, "potencia_contratada": "5,61"}