{"nombre_cliente": "Cleo Dorado Jara", "dni_cliente": "71518590K", "calle_cliente": "Calle Peña Arcipreste", "cp_cliente": "18615", "población_cliente": "Los", "provincia_cliente": "Granada", "nombre_comercializadora": null, "cif_comercializadora": "B87166435", "dirección_comercializadora": "C/ VELAZQUEZ Nº4 - 1º,", "cp_comercializadora": "28001", "población_comercializadora": "Madrid", "provincia_comercializadora": "Madrid", "número_factura": "G1426733123", "inicio_periodo": "28.11.1997", "fin_periodo": "27.01.1998", "importe_factura": "334,48", "fecha_cargo": "01.02.1998", "consumo_periodo": 1270, "potencia_contratada": "2,463"}