{"nombre_cliente": null, "dni_cliente": "93888266N", "calle_cliente": null, "cp_cliente": null, "población_cliente": null, "provincia_cliente": null, "nombre_comercializadora": null, "cif_comercializadora": "F94090792", "dirección_comercializadora": null, "cp_comercializadora": null, "población_comercializadora": null, "provincia_comercializadora": null, "número_factura": "H1012605349", "inicio_periodo": "24.10.2005", "fin_periodo": "23.12.2005", "importe_factura": "115,12", "fecha_cargo": null, "consumo_periodo": 308, "potencia_contratada": []}