{"nombre_cliente": null, "dni_cliente": "77424923T", "calle_cliente": null, "cp_cliente": null, "población_cliente": null, "provincia_cliente": null, "nombre_comercializadora": null, "cif_comercializadora": "B98717457", "dirección_comercializadora": null, "cp_comercializadora": null, "población_comercializadora": null, "provincia_comercializadora": null, "número_factura": "BZ4288915190", "inicio_periodo": "18.02.2018", "fin_periodo": "20.03.2018", "importe_factura": "68,38", "fecha_cargo": null, "consumo_periodo": 181, "potencia_contratada": []}