{"nombre_cliente": "JUVENCIO PALAZUELOS ESCOBEDO", "dni_cliente": "11054862G", "calle_cliente": "Camino de los Pajarejos", "cp_cliente": "46869", "población_cliente": "Atzeneta", "provincia_cliente": "Valencia", "nombre_comercializadora": "ALTERNA OPERADOR INTEGRAL, S.L", "cif_comercializadora": "B87075982", "dirección_comercializadora": "Jose Echegaray 1", "cp_comercializadora": "28232", "población_comercializadora": "Las", "provincia_comercializadora": "Madrid", "número_factura": "HS5969382372", "inicio_periodo": "11.11.2013", "fin_periodo": "10.01.2014", "importe_factura": "42,02", "fecha_cargo": "15.01.2014", "consumo_periodo": 34, "potencia_contratada": "4,615"}