{"nombre_cliente": null, "dni_cliente": "97089620L", "calle_cliente": null, "cp_cliente": null, "población_cliente": null, "provincia_cliente": null, "nombre_comercializadora": null, "cif_comercializadora": "A73137788", "dirección_comercializadora": null, "cp_comercializadora": null, "población_comercializadora": null, "provincia_comercializadora": null, "número_factura": "SA3810966826", "inicio_periodo": "22.04.1990", "fin_periodo": "21.06.1990", "importe_factura": "292,88", "fecha_cargo": null, "consumo_periodo": 890, "potencia_contratada": []}